pickart/__init__.py
pickart/__main__.py
pickart/colour.py
pickart/colour_formats.py
pickart/constatnts.py
pickart/converter.py
pickart/errors.py
pickart/pickart_file.py
pickart/pickart_file_data.py
pickart/restricted_unpickler.py
pickart-2.0.0.dist-info/METADATA
pickart-2.0.0.dist-info/WHEEL
pickart-2.0.0.dist-info/licenses/LICENSE
pickart-2.0.0.dist-info/RECORD
