Metadata-Version: 2.4
Name: pickart
Version: 2.0.0
Summary: This is helper package for game called 'Colouring art.
Project-URL: Homepage, https://github.com/AntynK/Pickart
Project-URL: Repository, https://github.com/AntynK/Pickart.git
Project-URL: Issues, https://github.com/AntynK/Pickart/issues
Author: Andrii Karandashov
License-Expression: MIT
License-File: LICENSE
Keywords: Game,Painting,Pygame
Classifier: Programming Language :: Python :: 3
Classifier: Programming Language :: Python :: 3.9
Requires-Python: >=3.9
